sklearn_prg/__init__.py
sklearn_prg/metrics.py
sklearn_prg-0.1.3.dist-info/licenses/LICENSE
sklearn_prg-0.1.3.dist-info/METADATA
sklearn_prg-0.1.3.dist-info/WHEEL
sklearn_prg-0.1.3.dist-info/top_level.txt
sklearn_prg-0.1.3.dist-info/RECORD
