Metadata-Version: 2.4
Name: sklearn_prg
Version: 0.1.3
Summary: Precision-Recall-Gain curves and metrics for scikit-learn
Author-email: Andrew Burkard <andrewburkard@gmail.com>
License-Expression: MIT
Project-URL: Homepage, https://github.com/aburkard/sklearn_prg
Classifier: Programming Language :: Python :: 3
Classifier: Intended Audience :: Science/Research
Classifier: Topic :: Scientific/Engineering :: Artificial Intelligence
Requires-Python: >=3.8
License-File: LICENSE
Requires-Dist: numpy>=1.20
Requires-Dist: scikit-learn>=1.0
Requires-Dist: matplotlib>=3.0
Dynamic: license-file
